__init__.py
lepconfigparse/__init__.py
lepconfigparse/argparsing.py
lepconfigparse/manager.py
lepconfigparse/loaders/__init__.py
lepconfigparse/loaders/json.py
lepconfigparse/loaders/loader.py
lepconfigparse/nesting/__init__.py
lepconfigparse/nesting/keyconvert.py
lepconfigparse/nesting/keylines.py
lepconfigparse/nesting/nesting.py
lepecinconfigparse-0.0.2.dist-info/LICENSE
lepecinconfigparse-0.0.2.dist-info/METADATA
lepecinconfigparse-0.0.2.dist-info/WHEEL
lepecinconfigparse-0.0.2.dist-info/top_level.txt
lepecinconfigparse-0.0.2.dist-info/RECORD
