Metadata-Version: 2.1
Name: lepecinconfigparse
Version: 0.0.2
Summary: Package for setting, saving and loading config files.
Author-email: Ivan Silajev <evantrulife@gmail.com>
Project-URL: Homepage, https://github.com/Lepecin/configparse
Classifier: Programming Language :: Python :: 3
Classifier: License :: OSI Approved :: MIT License
Classifier: Operating System :: OS Independent
Requires-Python: >=3.11.4
License-File: LICENSE
